ocrd_wrap/__init__.py
ocrd_wrap/cli.py
ocrd_wrap/config.py
ocrd_wrap/ocrd-tool.json
ocrd_wrap/param_im6convert-denoise-raw.json
ocrd_wrap/param_scribo-cli-binarize-sauvola-ms-split.json
ocrd_wrap/shell.py
ocrd_wrap/skimage_binarize.py
ocrd_wrap/skimage_denoise.py
ocrd_wrap/skimage_denoise_raw.py
ocrd_wrap/skimage_normalize.py
ocrd_wrap-0.1.8.dist-info/LICENSE
ocrd_wrap-0.1.8.dist-info/METADATA
ocrd_wrap-0.1.8.dist-info/WHEEL
ocrd_wrap-0.1.8.dist-info/entry_points.txt
ocrd_wrap-0.1.8.dist-info/top_level.txt
ocrd_wrap-0.1.8.dist-info/RECORD
