Metadata-Version: 2.1
Name: ocrd-wrap
Version: 0.1.8
Summary: OCR-D wrapper for arbitrary coords-preserving image operations
Home-page: https://github.com/bertsky/ocrd_wrap
Author: Robert Sachunsky
Author-email: sachunsky@informatik.uni-leipzig.de
License: MIT
License-File: LICENSE
Requires-Dist: ocrd (>=2.18)
Requires-Dist: click (>=7.0)
Requires-Dist: scipy
Requires-Dist: numpy (>=1.17.0)
Requires-Dist: pillow (>=7.1.2)
Requires-Dist: scikit-image (>=0.17.2)
